[
    {
        "id": "1",
        "name": "blach-u",
        "GitHub":"https://github.com/blach-u"
    },
    {
        "id": "2",
        "name": "jaruto7",
        "GitHub":"https://github.com/jaruto7"
    },
    {
        "id": "3",
        "name": "joszo",
        "GitHub":"https://github.com/joszo"
    },
    {
        "id": "4",
        "name": "Kamper360",
        "GitHub":"https://github.com/Kamper360"
    },
    {
        "id": "5",
        "name": "Rekert",
        "GitHub":"https://github.com/Rekert"
    },
    {
        "id": "6",
        "name": "SebastianWesolowski",
        "GitHub":"https://github.com/SebastianWesolowski"
    }
]


